{
  "type": "minecraft:chest",
  "pools": [
    {
      "rolls": {
        "min": 1,
        "max": 3
      },
      "entries": [
        {
          "type": "minecraft:loot_table",
          "value": "cobblemon_aether_nether:generic/cobblemon/balls_t1"
        }
      ]
    },
    {
      "rolls": {
        "min": 1,
        "max": 2
      },
      "entries": [
        {
          "type": "minecraft:loot_table",
          "value": "cobblemon_aether_nether:generic/cobblemon/berries"
        }
      ]
    },
    {
      "rolls": {
        "min": 1,
        "max": 2
      },
      "entries": [
        {
          "type": "minecraft:loot_table",
          "value": "cobblemon_aether_nether:generic/cobblemon/medicine"
        }
      ],
      "conditions": [
        {
          "condition": "minecraft:random_chance",
          "chance": 0.5
        }
      ]
    },
    {
      "rolls": 1,
      "entries": [
        {
          "type": "minecraft:loot_table",
          "value": "cobblemon_aether_nether:generic/cobblemon/held_items_t1"
        }
      ],
      "conditions": [
        {
          "condition": "minecraft:random_chance",
          "chance": 0.5
        }
      ]
    },
    {
      "rolls": 1,
      "entries": [
        {
          "type": "minecraft:loot_table",
          "value": "cobblemon_aether_nether:generic/cobblemon/held_items_t2"
        }
      ],
      "conditions": [
        {
          "condition": "minecraft:random_chance",
          "chance": 0.2
        }
      ]
    },
    {
      "rolls": 1,
      "entries": [
        {
          "type": "minecraft:loot_table",
          "value": "cobblemon_aether_nether:generic/cobblemon/held_items_t3"
        }
      ],
      "conditions": [
        {
          "condition": "minecraft:random_chance",
          "chance": 0.05
        }
      ]
    },
    {
      "rolls": 1,
      "entries": [
        {
          "type": "minecraft:loot_table",
          "value": "cobblemon_aether_nether:generic/cobblemon/evolution_items"
        }
      ],
      "conditions": [
        {
          "condition": "minecraft:random_chance",
          "chance": 0.2
        }
      ]
    },
    {
      "rolls": {
        "min": 1,
        "max": 5
      },
      "entries": [
        {
          "type": "minecraft:loot_table",
          "value": "cobblemon_aether_nether:generic/candy/candy_t1"
        }
      ]
    },
    {
      "rolls": {
        "min": 1,
        "max": 2
      },
      "entries": [
        {
          "type": "minecraft:loot_table",
          "value": "cobblemon_aether_nether:generic/candy/candy_t2"
        }
      ],
      "conditions": [
        {
          "condition": "minecraft:random_chance",
          "chance": 0.1
        }
      ]
    },
    {
      "rolls": {
        "min": 1,
        "max": 3
      },
      "entries": [
        {
          "type": "minecraft:loot_table",
          "value": "cobblemon_aether_nether:generic/cobblemon/noigrumes"
        }
      ]
    },
    {
      "rolls": {
        "min": 1,
        "max": 2
      },
      "entries": [
        {
          "type": "minecraft:item",
          "name": "minecraft:iron_ingot",
          "functions": [
            {
              "function": "minecraft:set_count",
              "count": {
                "min": 1,
                "max": 4
              }
            }
          ]
        }
      ]
    }
  ]
}
