{
    "neededUninstalledMods":  [

                              ],
    "neededInstalledMods":  [

                            ],
    "spawns":  [
                   {
                       "pokemon":  "brutebonnet",
                       "id":  "brutebonnet-aether-1",
                       "presets":  [
                                       "natural"
                                   ],
                       "bucket":  "uncommon",
                       "type":  "pokemon",
                       "level":  "55-60",
                       "spawnablePositionType":  "grounded",
                       "weight":  2,
                       "condition":  {
                                         "biomes":  [
                                                        "#aether:is_aether"
                                                    ]
                                     }
                   }
               ],
    "enabled":  true
}

